__init__.py
alastr/__init__.py
alastr/cli.py
alastr/main.py
alastr/analyses/__init__.py
alastr/analyses/lexicon/__init__.py
alastr/analyses/lexicon/corelex.py
alastr/analyses/lexicon/lexicon.py
alastr/analyses/mechanics/__init__.py
alastr/analyses/mechanics/mechanics.py
alastr/analyses/morphology/__init__.py
alastr/analyses/morphology/morphology.py
alastr/analyses/ngrams/__init__.py
alastr/analyses/ngrams/ngrams.py
alastr/analyses/phonology/__init__.py
alastr/analyses/phonology/phonology.py
alastr/analyses/semantics/__init__.py
alastr/analyses/semantics/semantic_scoring.py
alastr/analyses/semantics/semantics.py
alastr/analyses/syntax/__init__.py
alastr/analyses/syntax/syntax.py
alastr/backend/__init__.py
alastr/backend/etl/IOManager.py
alastr/backend/etl/SQLDaemon.py
alastr/backend/etl/Table.py
alastr/backend/etl/__init__.py
alastr/backend/nlp/NLPmodel.py
alastr/backend/nlp/__init__.py
alastr/backend/nlp/data_processing.py
alastr/backend/nlp/preprocessing.py
alastr/backend/nlp/sample_prep.py
alastr/backend/tools/Tier.py
alastr/backend/tools/__init__.py
alastr/backend/tools/auxiliary.py
alastr/backend/tools/config_io.py
alastr/backend/tools/extract_imports.py
alastr/backend/tools/logger.py
alastr/utils/PipelineManager.py
alastr/utils/__init__.py
alastr/utils/misc.py
alastr/utils/section_config.py
alastr-0.0.1a1.dist-info/licenses/LICENSE.txt
alastr-0.0.1a1.dist-info/METADATA
alastr-0.0.1a1.dist-info/WHEEL
alastr-0.0.1a1.dist-info/entry_points.txt
alastr-0.0.1a1.dist-info/top_level.txt
alastr-0.0.1a1.dist-info/RECORD
