Metadata-Version: 2.4
Name: alastr
Version: 0.0.1a1
Summary: Aggregate Linguistic Analysis of Speech Transcripts for Research
Author: Nick McCloskey
License: MIT
Classifier: Programming Language :: Python :: 3
Classifier: License :: OSI Approved :: MIT License
Classifier: Operating System :: OS Independent
Requires-Python: >=3.12
License-File: LICENSE.txt
Requires-Dist: PyPDF2
Requires-Dist: afinn
Requires-Dist: benepar
Requires-Dist: dendropy
Requires-Dist: docx2txt
Requires-Dist: g2p-en
Requires-Dist: language-tool-python
Requires-Dist: lexicalrichness
Requires-Dist: matplotlib
Requires-Dist: nltk
Requires-Dist: NRCLex
Requires-Dist: numpy
Requires-Dist: openpyxl
Requires-Dist: pandas
Requires-Dist: py-readability-metrics
Requires-Dist: PyYAML
Requires-Dist: reportlab
Requires-Dist: scikit-learn
Requires-Dist: scipy
Requires-Dist: seaborn
Requires-Dist: spacy
Requires-Dist: svglib
Requires-Dist: textblob
Requires-Dist: textstat
Requires-Dist: tqdm
Requires-Dist: vaderSentiment
Requires-Dist: wordfreq
Requires-Dist: xlsxwriter
Requires-Dist: zss
Provides-Extra: transformers
Requires-Dist: torch; extra == "transformers"
Requires-Dist: transformers; extra == "transformers"
Requires-Dist: sentence-transformers; extra == "transformers"
Requires-Dist: accelerate; extra == "transformers"
Provides-Extra: topic-modeling
Requires-Dist: bertopic; extra == "topic-modeling"
Requires-Dist: umap-learn; extra == "topic-modeling"
Requires-Dist: hdbscan; extra == "topic-modeling"
Provides-Extra: viz
Requires-Dist: plotly; extra == "viz"
Requires-Dist: CairoSVG; extra == "viz"
Provides-Extra: web
Requires-Dist: streamlit; extra == "web"
Provides-Extra: dev
Requires-Dist: ipython; extra == "dev"
Requires-Dist: debugpy; extra == "dev"
Requires-Dist: pip-tools; extra == "dev"
Requires-Dist: pytest; extra == "dev"
Dynamic: license-file
